{
  "_class": "bitmap",
  "booleanOperation": 0,
  "clippingMask": "{{0, 0}, {1, 1}}",
  "clippingMaskMode": 0,
  "do_objectID": "00C56E16-8444-479D-9674-685AE53A9188",
  "exportOptions": {
    "_class": "exportOptions",
    "do_objectID": "A24946A7-4BA0-4D89-A871-188D9A7FB7EA",
    "exportFormats": [
    ],
    "includedLayerIds": [
    ],
    "layerOptions": 0,
    "shouldTrim": false
  },
  "fillReplacesImage": false,
  "frame": {
    "_class": "rect",
    "constrainProportions": true,
    "do_objectID": "B2D14F8F-AB6E-4BAC-A966-37A7345DC629",
    "height": 460,
    "width": 654.5,
    "x": -0.5,
    "y": -0.25
  },
  "hasClippingMask": false,
  "image": {
    "_class": "MSJSONFileReference",
    "_ref": "images/86f8e5b3cc41c9031d6d8f9eb2fea8b0d419f1ab.png",
    "_ref_class": "MSImageData"
  },
  "intendedDPI": 0,
  "isFixedToViewport": false,
  "isFlippedHorizontal": false,
  "isFlippedVertical": false,
  "isLocked": false,
  "isVisible": true,
  "layerListExpandedType": 0,
  "name": "Overlay",
  "nameIsFixed": true,
  "resizingConstraint": 63,
  "resizingType": 0,
  "rotation": 0,
  "shouldBreakMaskChain": false,
  "style": {
    "_class": "style",
    "blur": {
      "_class": "blur",
      "center": "{0.5, 0.5}",
      "do_objectID": "ABF82614-2572-4037-8D2E-34B30065132A",
      "isEnabled": false,
      "motionAngle": 0,
      "radius": 2.5,
      "saturation": 1,
      "type": 0
    },
    "contextSettings": {
      "_class": "graphicsContextSettings",
      "blendMode": 7,
      "do_objectID": "39478B09-57BB-4ABC-A428-96965BAF4469",
      "opacity": 1
    },
    "do_objectID": "50195D29-89D5-41E3-8753-F1A313BF8247",
    "endMarkerType": 0,
    "miterLimit": 10,
    "startMarkerType": 0,
    "windingRule": 1
  }
}