{
  "_class": "group",
  "do_objectID": "421023F3-45BC-493D-BFF2-A22596376787",
  "exportOptions": {
    "_class": "exportOptions",
    "exportFormats": [
    ],
    "includedLayerIds": [
    ],
    "layerOptions": 0,
    "shouldTrim": false
  },
  "frame": {
    "_class": "rect",
    "constrainProportions": false,
    "height": 44,
    "width": 150,
    "x": 20,
    "y": 494
  },
  "hasClickThrough": false,
  "isFlippedHorizontal": false,
  "isFlippedVertical": false,
  "isLocked": false,
  "isVisible": true,
  "layerListExpandedType": 0,
  "layers": [
    {
      "class": "shapeGroup",
      "id": "C50FFEC4-C7BC-4267-A40D-F1DB4AF9331C"
    },
    {
      "class": "text",
      "id": "396B6A33-21B0-4F06-9612-4BE6AAF2F76A"
    }
  ],
  "name": "按钮",
  "nameIsFixed": true,
  "resizingConstraint": 63,
  "resizingType": 0,
  "rotation": 0,
  "shouldBreakMaskChain": false,
  "style": {
    "_class": "style",
    "endDecorationType": 0,
    "miterLimit": 10,
    "startDecorationType": 0
  }
}