{
  "_class": "group",
  "booleanOperation": 0,
  "clippingMaskMode": 0,
  "do_objectID": "19BDFCC8-2D5E-4FF7-8FA8-E73E3287423A",
  "exportOptions": {
    "_class": "exportOptions",
    "exportFormats": [
    ],
    "includedLayerIds": [
    ],
    "layerOptions": 0,
    "shouldTrim": false
  },
  "frame": {
    "_class": "rect",
    "constrainProportions": false,
    "height": 353,
    "width": 800,
    "x": 0,
    "y": 0
  },
  "hasClickThrough": false,
  "hasClippingMask": false,
  "isFixedToViewport": false,
  "isFlippedHorizontal": false,
  "isFlippedVertical": false,
  "isLocked": false,
  "isVisible": true,
  "layerListExpandedType": 0,
  "layers": [
    {
      "class": "group",
      "id": "16F68238-D2D8-43FC-ADE5-4862AF056F81"
    },
    {
      "class": "group",
      "id": "5ECB8AF0-8191-437C-B8AA-EFED49F3D511"
    },
    {
      "class": "oval",
      "id": "83172729-5787-4B27-8988-63920B1F48E7"
    },
    {
      "class": "shapePath",
      "id": "00308830-3DC5-48B2-88AF-6D40CB26FDD2"
    },
    {
      "class": "shapePath",
      "id": "34DBBB29-8744-41B2-9E37-B1B92E4E75B9"
    },
    {
      "class": "shapePath",
      "id": "F2460CEA-2707-45C6-B160-2740D69D71B5"
    },
    {
      "class": "shapePath",
      "id": "FDB996F6-F1BB-424B-853C-2D0588078646"
    }
  ],
  "name": "Group 2 Copy",
  "nameIsFixed": false,
  "resizingConstraint": 63,
  "resizingType": 0,
  "rotation": 0,
  "shouldBreakMaskChain": false,
  "style": {
    "_class": "style",
    "endMarkerType": 0,
    "miterLimit": 10,
    "startMarkerType": 0,
    "windingRule": 1
  }
}