{
  "_class": "bitmap",
  "booleanOperation": 0,
  "clippingMask": "{{0, 0}, {1, 1}}",
  "clippingMaskMode": 0,
  "do_objectID": "9576F7B6-F44E-47FD-9B23-CB513199801D",
  "exportOptions": {
    "_class": "exportOptions",
    "do_objectID": "02C4E119-A729-45B7-81B2-53609CFE74B9",
    "exportFormats": [
    ],
    "includedLayerIds": [
    ],
    "layerOptions": 0,
    "shouldTrim": false
  },
  "fillReplacesImage": false,
  "frame": {
    "_class": "rect",
    "constrainProportions": true,
    "do_objectID": "B774F7AB-44C6-4169-AD81-243B9CDF68F0",
    "height": 460,
    "width": 654.5,
    "x": -0.5,
    "y": -0.25
  },
  "hasClippingMask": false,
  "image": {
    "_class": "MSJSONFileReference",
    "_ref": "images/86f8e5b3cc41c9031d6d8f9eb2fea8b0d419f1ab.png",
    "_ref_class": "MSImageData"
  },
  "intendedDPI": 0,
  "isFixedToViewport": false,
  "isFlippedHorizontal": false,
  "isFlippedVertical": false,
  "isLocked": false,
  "isVisible": true,
  "layerListExpandedType": 0,
  "name": "Overlay",
  "nameIsFixed": true,
  "resizingConstraint": 63,
  "resizingType": 0,
  "rotation": 0,
  "shouldBreakMaskChain": false,
  "style": {
    "_class": "style",
    "blur": {
      "_class": "blur",
      "center": "{0.5, 0.5}",
      "do_objectID": "84F89243-5F16-4279-AD61-01D41DA3D3DE",
      "isEnabled": false,
      "motionAngle": 0,
      "radius": 2.5,
      "saturation": 1,
      "type": 0
    },
    "contextSettings": {
      "_class": "graphicsContextSettings",
      "blendMode": 7,
      "do_objectID": "3C615E3D-B76C-4710-9C5A-F6CFC7FD6827",
      "opacity": 1
    },
    "do_objectID": "05E079F0-5C1B-4F82-9FEB-34179756E350",
    "endMarkerType": 0,
    "miterLimit": 10,
    "startMarkerType": 0,
    "windingRule": 1
  }
}